<?xml version="1.0" encoding="utf-8"?>
<SkillDatas>
  <SkillData templateID="1" name="화염구" type="Projectile" prefab="FireProjectile.prefab" damage="1000" speed="2" >
  </SkillData>
  <SkillData templateID="10" name="평타" type="Melee" prefab="EgoSword.prefab" damage="1000" >
  </SkillData>
  <SkillData templateID="20" name="평타" type="Melee" prefab="Fireball.prefab" damage="1000" >
  </SkillData>

  <!--<SkillData templateID="1" name="화염구" type="projectile" prefab="FireProjectile.prefab" damage="1000">
		<ProjectileData speed="3" damage="10" hitCount="1">
			<OnHit>
				<HitEffect type="buff" bufType="12" templateID="30"></HitEffect>
				<HitEffect type="buff" bufType="12" templateID="30"></HitEffect>
				<HitEffect type="buff" bufType="12" templateID="30"></HitEffect>
				<HitEffect type="buff" bufType="12" templateID="30"></HitEffect>
			</OnHit>
		</ProjectileData>
		<SpawnData>			
		</SpawnData>
	</SkillData>
	<SkillData templateID="11" nextID="12" name="평타" type="melee" prefab="" damage="1000">
	</SkillData>
	<SkillData templateID="12" nextID="13" name="평타" type="melee" prefab="" damage="1000">
	</SkillData>
	<SkillData templateID="13" nextID="14" name="평타" type="melee" prefab="" damage="1000">
	</SkillData>
	<SkillData templateID="14" nextID="15" name="평타" type="melee" prefab="" damage="1000">
	</SkillData>
	<SkillData templateID="15" name="평타" type="melee" prefab="" damage="1000">
	</SkillData>-->
</SkillDatas>